{"OpenedDocuments":"[\"Main.xaml\",\"Google/ariba-invoice-entry-standard-google-new.xaml\",\"Google/ariba-credit-click-into-multi_new.xaml\",\"Google/ariba-invoice-entry-poupdate-google.xaml\",\"Process.xaml\",\"Google/ariba-sharepoint-download-invoice.xaml\"]","ProjectWatches":"{\"Value\":[{\"Id\":\"3b667bb1-722b-4129-8056-cd6b04f84809\",\"Expression\":\"strAttribute\"}]}","ProjectBreakpoints":"{\"Value\":{\"Process.xaml\":[{\"ConditionalExpression\":null,\"ActionExpression\":null,\"ExpectedHitCounter\":null,\"ShouldContinueAfterAction\":false,\"IsTransient\":false,\"IsEnabled\":true,\"Id\":\"1e844921-d08b-4e13-a4d3-493709ec0422\",\"ActivityIdRef\":\"AddDataRow_9\",\"ActivityId\":\"1.301\",\"ActivityName\":\"Add Data Row\"},{\"ConditionalExpression\":null,\"ActionExpression\":null,\"ExpectedHitCounter\":null,\"ShouldContinueAfterAction\":false,\"IsTransient\":false,\"IsEnabled\":true,\"Id\":\"49fdad9a-4c61-4344-abfb-823d3b04fa16\",\"ActivityIdRef\":\"Office365ApplicationScope_1\",\"ActivityId\":\"1.18\",\"ActivityName\":\"Microsoft Office 365 Scope : To SEND outlook mail\"},{\"ConditionalExpression\":null,\"ActionExpression\":null,\"ExpectedHitCounter\":null,\"ShouldContinueAfterAction\":false,\"IsTransient\":false,\"IsEnabled\":true,\"Id\":\"6e6abd47-bc92-45e8-9625-a6244a740e78\",\"ActivityIdRef\":\"GetRobotCredential_11\",\"ActivityId\":\"1.37\",\"ActivityName\":\"Get Credential : For outlook\"},{\"ConditionalExpression\":null,\"ActionExpression\":null,\"ExpectedHitCounter\":null,\"ShouldContinueAfterAction\":false,\"IsTransient\":false,\"IsEnabled\":true,\"Id\":\"9626711d-6087-459f-9901-5507805d9b13\",\"ActivityIdRef\":\"InvokeWorkflowFile_81\",\"ActivityId\":\"1.312\",\"ActivityName\":\"Invoke Workflow File- To Enter Invoice Details\"}],\"Google/ariba-invoice-entry-standard-google-new.xaml\":[{\"ConditionalExpression\":null,\"ActionExpression\":null,\"ExpectedHitCounter\":null,\"ShouldContinueAfterAction\":false,\"IsTransient\":false,\"IsEnabled\":true,\"Id\":\"50227bf2-9953-43fb-a0fa-d19503405c89\",\"ActivityIdRef\":\"InvokeWorkflowFile_3\",\"ActivityId\":\"1.8\",\"ActivityName\":\"ariba-invoice-entry-poupdate-google.xaml - Invoke Workflow File\"}],\"Google/ariba-invoice-entry-poupdate-google.xaml\":[{\"ConditionalExpression\":null,\"ActionExpression\":null,\"ExpectedHitCounter\":null,\"ShouldContinueAfterAction\":false,\"IsTransient\":false,\"IsEnabled\":true,\"Id\":\"629af048-8972-4331-b4e9-1badf46168ad\",\"ActivityIdRef\":\"GetAttribute_1\",\"ActivityId\":\"1.85\",\"ActivityName\":\"Get Attribute 'DIV'\"}]}}","LibraryProjectSettings":"{\"IncludeSourcesByDefault\":true,\"CompileExpressions\":true,\"ReadyToRun\":false,\"DefaultActivitiesRootCategories\":[null]}"}